atk/tls_checker/__init__.py
atk/tls_checker/__main__.py
atk/tls_checker/main.py
atk_tls_checker-0.2.0.dist-info/METADATA
atk_tls_checker-0.2.0.dist-info/WHEEL
atk_tls_checker-0.2.0.dist-info/RECORD
