Metadata-Version: 2.1
Name: atk-tls-checker
Version: 0.2.0
Summary: 
Author: Panu Oksiala
Author-email: panu@oksiala.fi
Requires-Python: >=3.10,<4.0
Classifier: Programming Language :: Python :: 3
Classifier: Programming Language :: Python :: 3.10
Classifier: Programming Language :: Python :: 3.11
Requires-Dist: fastapi (>=0.103.0,<0.104.0)
Requires-Dist: pydantic (>=2.3.0,<3.0.0)
Requires-Dist: pyopenssl (>=23.2.0,<24.0.0)
Requires-Dist: sentry-sdk[fastapi] (>=1.29.2,<2.0.0)
